pibooth_dropbox/__init__.py
pibooth_dropbox/flow.py
pibooth_dropbox/plugin.py
pibooth_dropbox-0.0.3.dist-info/LICENSE
pibooth_dropbox-0.0.3.dist-info/METADATA
pibooth_dropbox-0.0.3.dist-info/WHEEL
pibooth_dropbox-0.0.3.dist-info/entry_points.txt
pibooth_dropbox-0.0.3.dist-info/top_level.txt
pibooth_dropbox-0.0.3.dist-info/RECORD
