Metadata-Version: 2.1
Name: pibooth-dropbox
Version: 0.0.3
Summary: Pibooth plugin to upload pictures on Dropbox.
Home-page: https://github.com/pibooth/pibooth-dropbox
Author: Martin Mhilcher
License: GPLv3
Download-URL: https://github.com/pibooth/pibooth-dropbox/archive/0.0.3.tar.gz
Keywords: Raspberry Pi,camera,photobooth
Platform: unix
Platform: linux
Classifier: Development Status :: 5 - Production/Stable
Classifier: Environment :: Other Environment
Classifier: Intended Audience :: Developers
Classifier: Intended Audience :: End Users/Desktop
Classifier: License :: OSI Approved :: GNU General Public License v3 or later (GPLv3+)
Classifier: Operating System :: POSIX :: Linux
Classifier: Programming Language :: Python :: 3.6
Classifier: Programming Language :: Python :: 3.7
Classifier: Programming Language :: Python :: 3.8
Classifier: Programming Language :: Python :: 3.9
Classifier: Natural Language :: English
Classifier: Topic :: Multimedia :: Graphics :: Capture :: Digital Camera
Requires-Python: >=3.6
License-File: LICENSE
Requires-Dist: pibooth (>=2.0.0)
Requires-Dist: dropbox (>=11.29.0)
